_bpy_internal/__init__.pyi
_bpy_internal/py.typed
_bpy_internal/addons/__init__.pyi
_bpy_internal/addons/cli/__init__.pyi
_bpy_internal/extensions/__init__.pyi
_bpy_internal/extensions/junction_module/__init__.pyi
_bpy_internal/extensions/stale_file_manager/__init__.pyi
_bpy_internal/extensions/wheel_manager/__init__.pyi
_bpy_internal/freedesktop/__init__.pyi
_bpy_internal/grease_pencil/__init__.pyi
_bpy_internal/grease_pencil/stroke/__init__.pyi
_bpy_internal/system_info/__init__.pyi
_bpy_internal/system_info/text_generate_runtime/__init__.pyi
_bpy_internal/system_info/url_prefill_runtime/__init__.pyi
_bpy_internal/system_info/url_prefill_startup/__init__.pyi
addon_utils/__init__.pyi
addon_utils/py.typed
animsys_refactor/__init__.pyi
animsys_refactor/py.typed
aud/__init__.pyi
aud/py.typed
bgl/__init__.pyi
bgl/py.typed
bl_app_override/__init__.pyi
bl_app_override/py.typed
bl_app_override/helpers/__init__.pyi
bl_app_template_utils/__init__.pyi
bl_app_template_utils/py.typed
bl_console_utils/__init__.pyi
bl_console_utils/py.typed
bl_console_utils/autocomplete/__init__.pyi
bl_console_utils/autocomplete/complete_calltip/__init__.pyi
bl_console_utils/autocomplete/complete_import/__init__.pyi
bl_console_utils/autocomplete/complete_namespace/__init__.pyi
bl_console_utils/autocomplete/intellisense/__init__.pyi
bl_i18n_utils/__init__.pyi
bl_i18n_utils/py.typed
bl_i18n_utils/bl_extract_messages/__init__.pyi
bl_i18n_utils/merge_po/__init__.pyi
bl_i18n_utils/settings/__init__.pyi
bl_i18n_utils/utils/__init__.pyi
bl_i18n_utils/utils_cli/__init__.pyi
bl_i18n_utils/utils_languages_menu/__init__.pyi
bl_i18n_utils/utils_rtl/__init__.pyi
bl_keymap_utils/__init__.pyi
bl_keymap_utils/py.typed
bl_keymap_utils/io/__init__.pyi
bl_keymap_utils/keymap_from_toolbar/__init__.pyi
bl_keymap_utils/keymap_hierarchy/__init__.pyi
bl_keymap_utils/platform_helpers/__init__.pyi
bl_keymap_utils/versioning/__init__.pyi
bl_math/__init__.pyi
bl_math/py.typed
bl_operators/__init__.pyi
fake_bpy_module_4.3-20250130.dist-info/METADATA
fake_bpy_module_4.3-20250130.dist-info/WHEEL
fake_bpy_module_4.3-20250130.dist-info/top_level.txt
fake_bpy_module_4.3-20250130.dist-info/RECORD
